{
  "DIA_Cortez_VZ_Ambient_03_02": "J'ai peur ? Pour qui me prends-tu !",
  "DIA_Cortez_VZ_Ambient_03_03": "Hmm... Si une telle bête était traînée jusqu'à notre arène... quel spectacle ce serait !",
  "DIA_Cortez_VZ_Ambient_03_01": "J'en ai déjà vu d'autres. Le plus important, c'est de se rappeler que ces endroits cachent souvent des trésors précieux. Garde les yeux ouverts.",
  "DIA_Cortez_VZ_Q514_EndThis_03_01": "Bon, tu as joué les explorateurs, maintenant rends tout ce que tu as trouvé dans la crypte.",
  "DIA_Cortez_VZ_Q514_EndThis_Crazy_15_01": "Tu es fou ?",
  "DIA_Cortez_VZ_Q514_EndThis_Crazy_03_02": "Tu crois que je vais me contenter des restes pendant que tu prends le butin le plus précieux ?",
  "DIA_Cortez_VZ_Q514_EndThis_Crazy_03_03": "J'en ai marre de pourrir sur cette fichue Archolos. Toi et ton trésor êtes mon billet pour une vie de débauche à Vengard.",
  "DIA_Cortez_VZ_Q514_EndThis_No_15_01": "Tu n'auras rien.",
  "DIA_Cortez_VZ_Q514_EndThis_Yes_15_01": "Tiens, l'épée est à toi."
}
